odoo8_addon_l10n_es_aeat_mod340_cash_basis-8.0.1.0.0-py2.7-nspkg.pth
odoo_addons/l10n_es_aeat_mod340_cash_basis/__openerp__.py
odoo_addons/l10n_es_aeat_mod340_cash_basis/__init__.py
odoo_addons/l10n_es_aeat_mod340_cash_basis/README.rst
odoo_addons/l10n_es_aeat_mod340_cash_basis/wizard/calculate_mod340_records.py
odoo_addons/l10n_es_aeat_mod340_cash_basis/wizard/__init__.py
odoo_addons/l10n_es_aeat_mod340_cash_basis/static/description/icon_source.svg
odoo_addons/l10n_es_aeat_mod340_cash_basis/static/description/icon.png
odoo8_addon_l10n_es_aeat_mod340_cash_basis-8.0.1.0.0.dist-info/top_level.txt
odoo8_addon_l10n_es_aeat_mod340_cash_basis-8.0.1.0.0.dist-info/WHEEL
odoo8_addon_l10n_es_aeat_mod340_cash_basis-8.0.1.0.0.dist-info/RECORD
odoo8_addon_l10n_es_aeat_mod340_cash_basis-8.0.1.0.0.dist-info/metadata.json
odoo8_addon_l10n_es_aeat_mod340_cash_basis-8.0.1.0.0.dist-info/DESCRIPTION.rst
odoo8_addon_l10n_es_aeat_mod340_cash_basis-8.0.1.0.0.dist-info/METADATA
odoo8_addon_l10n_es_aeat_mod340_cash_basis-8.0.1.0.0.dist-info/namespace_packages.txt
