Metadata-Version: 2.0
Name: odoo8-addon-l10n-es-aeat-mod340-cash-basis
Version: 8.0.1.0.0
Summary: Extensión del modelo 340 para criterio de caja
Home-page: https://github.com/OCA/l10n-spain
Author: UNKNOWN
Author-email: UNKNOWN
License: AGPL-3
Platform: UNKNOWN
Requires-Dist: odoo (<9.0a,>=8.0a)
Requires-Dist: odoo8-addon-account-vat-on-payment
Requires-Dist: odoo8-addon-l10n-es-aeat-mod340
Classifier: Programming Language :: Python :: 2.7
Classifier: Framework :: Odoo
Classifier: License :: OSI Approved :: GNU Affero General Public License v3
